persistedstate/__init__.py
persistedstate/py.typed
persistedstate-25.1.dist-info/METADATA
persistedstate-25.1.dist-info/WHEEL
persistedstate-25.1.dist-info/licenses/LICENSE
persistedstate-25.1.dist-info/RECORD
