Metadata-Version: 2.4
Name: persistedstate
Version: 25.1
Summary: Ultra fast persistent store for small states in mapped YAML file
Project-URL: Homepage, https://github.com/presidento/persistedstate
Project-URL: Changelog, https://github.com/presidento/persistedstate/blob/main/CHANGELOG.md
Author-email: Máté Farkas <fm@farkas-mate.hu>
License-Expression: MIT
License-File: LICENSE
Classifier: Development Status :: 5 - Production/Stable
Classifier: Intended Audience :: Developers
Classifier: Intended Audience :: System Administrators
Classifier: License :: OSI Approved :: MIT License
Classifier: Operating System :: OS Independent
Classifier: Programming Language :: Python :: 3 :: Only
Classifier: Programming Language :: Python :: 3.9
Classifier: Programming Language :: Python :: 3.10
Classifier: Programming Language :: Python :: 3.11
Classifier: Programming Language :: Python :: 3.12
Classifier: Programming Language :: Python :: 3.13
Classifier: Programming Language :: Python :: 3.14
Classifier: Topic :: Utilities
Classifier: Typing :: Typed
Requires-Python: >=3.9
Requires-Dist: pyyaml
